hardstop/__init__.py
hardstop-0.0.1.dist-info/METADATA
hardstop-0.0.1.dist-info/WHEEL
hardstop-0.0.1.dist-info/top_level.txt
hardstop-0.0.1.dist-info/RECORD
