Metadata-Version: 2.4
Name: hardstop
Version: 0.0.1
Summary: The mechanical brake for AI-generated commands. Pre-execution safety validation for Claude Code.
Author-email: frmoretto <francesco.marinoni.moretto@gmail.com>
License-Expression: CC-BY-4.0
Project-URL: Homepage, https://github.com/frmoretto/hardstop
Project-URL: Repository, https://github.com/frmoretto/hardstop
Project-URL: Issues, https://github.com/frmoretto/hardstop/issues
Keywords: hardstop,ai-safety,command-validation,security,claude-code,mcp,pre-execution,fail-closed,llm,bash,shell
Classifier: Development Status :: 1 - Planning
Classifier: Intended Audience :: Developers
Classifier: Programming Language :: Python :: 3
Classifier: Programming Language :: Python :: 3.9
Classifier: Programming Language :: Python :: 3.10
Classifier: Programming Language :: Python :: 3.11
Classifier: Programming Language :: Python :: 3.12
Classifier: Topic :: Security
Classifier: Topic :: Software Development :: Quality Assurance
Requires-Python: >=3.9
